kbeta/__init__.py
kbeta/py.typed
kbeta/optim/__init__.py
kbeta/optim/kbeta_softmax.py
kbeta-1.0.0.dist-info/licenses/LICENSE
kbeta-1.0.0.dist-info/METADATA
kbeta-1.0.0.dist-info/WHEEL
kbeta-1.0.0.dist-info/top_level.txt
kbeta-1.0.0.dist-info/RECORD
