Metadata-Version: 2.4
Name: kbeta
Version: 1.0.0
Summary: Kourkoutas-β optimiser and demo workloads
Author: Stavros Kassinos
Project-URL: Homepage, https://github.com/sck-at-ucy/kbeta
Project-URL: Documentation, https://github.com/sck-at-ucy/kbeta
Project-URL: Repository, https://github.com/sck-at-ucy/kbeta
Classifier: Programming Language :: Python :: 3
Classifier: License :: OSI Approved :: MIT License
Classifier: Operating System :: MacOS :: MacOS X
Classifier: Intended Audience :: Science/Research
Classifier: Topic :: Scientific/Engineering :: Artificial Intelligence
Requires-Python: >=3.9
License-File: LICENSE
Requires-Dist: mlx
Provides-Extra: dev
Requires-Dist: pytest; extra == "dev"
Requires-Dist: ruff; extra == "dev"
Requires-Dist: numpy; extra == "dev"
Requires-Dist: matplotlib; extra == "dev"
Provides-Extra: repro
Requires-Dist: mlx==0.26.3; extra == "repro"
Requires-Dist: pytest; extra == "repro"
Requires-Dist: ruff; extra == "repro"
Requires-Dist: numpy; extra == "repro"
Requires-Dist: matplotlib; extra == "repro"
Dynamic: license-file
